{
    "generated":"2021-12-16 06:28",
    "en":[
        {
            "catalogID":"135e26fb6ce06dc59aa7da3330f16b6db6d16d9b",
            "entityID":"https://login.talisaspire.com/entity",
            "resourceName":"Talis Education Limited",
            "resourceProvider":{
                "name":"Talis Group Limited",
                "displayname":"Talis Education Limited",
                "url":"http://www.talisaspire.com/"
            },
            "resourceAttributes":{
                "required":[
                    "eduPersonTargetedID"
                ],
                "requested":[]
            },
            "description":"",
            "resourceContacts":[
                {
                    "type":"support",
                    "name":"Talis Support",
                    "email":"mailto:support@talis.com"
                },
                {
                    "type":"technical",
                    "name":"Authentication Support",
                    "email":"mailto:authentication@talis.com"
                }
            ],
            "info":"",
            "privacy":"",
            "entityCategories":[],
            "SirtfiSupport":[]
        }
    ],
    "fr":[
        {
            "catalogID":"135e26fb6ce06dc59aa7da3330f16b6db6d16d9b",
            "entityID":"https://login.talisaspire.com/entity",
            "resourceName":"Talis Education Limited",
            "resourceProvider":{
                "name":[],
                "displayname":[],
                "url":"http://www.talisaspire.com/"
            },
            "resourceAttributes":{
                "required":[
                    "eduPersonTargetedID"
                ],
                "requested":[]
            },
            "description":"",
            "resourceContacts":[
                {
                    "type":"support",
                    "name":"Talis Support",
                    "email":"mailto:support@talis.com"
                },
                {
                    "type":"technical",
                    "name":"Authentication Support",
                    "email":"mailto:authentication@talis.com"
                }
            ],
            "info":"",
            "privacy":"",
            "entityCategories":[],
            "SirtfiSupport":[]
        }
    ],
    "it":[
        {
            "catalogID":"135e26fb6ce06dc59aa7da3330f16b6db6d16d9b",
            "entityID":"https://login.talisaspire.com/entity",
            "resourceName":"Talis Education Limited",
            "resourceProvider":{
                "name":[],
                "displayname":[],
                "url":"http://www.talisaspire.com/"
            },
            "resourceAttributes":{
                "required":[
                    "eduPersonTargetedID"
                ],
                "requested":[]
            },
            "description":"",
            "resourceContacts":[
                {
                    "type":"support",
                    "name":"Talis Support",
                    "email":"mailto:support@talis.com"
                },
                {
                    "type":"technical",
                    "name":"Authentication Support",
                    "email":"mailto:authentication@talis.com"
                }
            ],
            "info":"",
            "privacy":"",
            "entityCategories":[],
            "SirtfiSupport":[]
        }
    ],
    "de":[
        {
            "catalogID":"135e26fb6ce06dc59aa7da3330f16b6db6d16d9b",
            "entityID":"https://login.talisaspire.com/entity",
            "resourceName":"Talis Education Limited",
            "resourceProvider":{
                "name":[],
                "displayname":[],
                "url":"http://www.talisaspire.com/"
            },
            "resourceAttributes":{
                "required":[
                    "eduPersonTargetedID"
                ],
                "requested":[]
            },
            "description":"",
            "resourceContacts":[
                {
                    "type":"support",
                    "name":"Talis Support",
                    "email":"mailto:support@talis.com"
                },
                {
                    "type":"technical",
                    "name":"Authentication Support",
                    "email":"mailto:authentication@talis.com"
                }
            ],
            "info":"",
            "privacy":"",
            "entityCategories":[],
            "SirtfiSupport":[]
        }
    ]
}