{
    "generated":"2022-05-30 20:27",
    "en":[
        {
            "catalogID":"7b1fb5bebc4b1f6609e54f274901933712fef673",
            "entityID":"https://historicaltexts.jisc.ac.uk/shibboleth",
            "resourceName":"Historical Texts",
            "resourceProvider":{
                "name":"Jisc",
                "displayname":"Historical Texts",
                "url":"https://jisc.ac.uk/"
            },
            "resourceAttributes":{
                "required":[],
                "requested":[]
            },
            "description":"Collections of texts from the late fifteenth to long nineteenth century",
            "resourceContacts":[
                {
                    "type":"support",
                    "name":"Historical Texts Helpdesk",
                    "email":"mailto:historicaltexts@jisc.ac.uk"
                },
                {
                    "type":"technical",
                    "name":"Jisc Cloud and Connectivity Services",
                    "email":"mailto:servicedesk@jisc.ac.uk"
                }
            ],
            "info":"",
            "privacy":"",
            "entityCategories":[],
            "SirtfiSupport":[]
        }
    ],
    "fr":[
        {
            "catalogID":"7b1fb5bebc4b1f6609e54f274901933712fef673",
            "entityID":"https://historicaltexts.jisc.ac.uk/shibboleth",
            "resourceName":"https://historicaltexts.jisc.ac.uk/shibboleth",
            "resourceProvider":{
                "name":[],
                "displayname":[],
                "url":"https://jisc.ac.uk/"
            },
            "resourceAttributes":{
                "required":[],
                "requested":[]
            },
            "description":"",
            "resourceContacts":[
                {
                    "type":"support",
                    "name":"Historical Texts Helpdesk",
                    "email":"mailto:historicaltexts@jisc.ac.uk"
                },
                {
                    "type":"technical",
                    "name":"Jisc Cloud and Connectivity Services",
                    "email":"mailto:servicedesk@jisc.ac.uk"
                }
            ],
            "info":"",
            "privacy":"",
            "entityCategories":[],
            "SirtfiSupport":[]
        }
    ],
    "it":[
        {
            "catalogID":"7b1fb5bebc4b1f6609e54f274901933712fef673",
            "entityID":"https://historicaltexts.jisc.ac.uk/shibboleth",
            "resourceName":"https://historicaltexts.jisc.ac.uk/shibboleth",
            "resourceProvider":{
                "name":[],
                "displayname":[],
                "url":"https://jisc.ac.uk/"
            },
            "resourceAttributes":{
                "required":[],
                "requested":[]
            },
            "description":"",
            "resourceContacts":[
                {
                    "type":"support",
                    "name":"Historical Texts Helpdesk",
                    "email":"mailto:historicaltexts@jisc.ac.uk"
                },
                {
                    "type":"technical",
                    "name":"Jisc Cloud and Connectivity Services",
                    "email":"mailto:servicedesk@jisc.ac.uk"
                }
            ],
            "info":"",
            "privacy":"",
            "entityCategories":[],
            "SirtfiSupport":[]
        }
    ],
    "de":[
        {
            "catalogID":"7b1fb5bebc4b1f6609e54f274901933712fef673",
            "entityID":"https://historicaltexts.jisc.ac.uk/shibboleth",
            "resourceName":"https://historicaltexts.jisc.ac.uk/shibboleth",
            "resourceProvider":{
                "name":[],
                "displayname":[],
                "url":"https://jisc.ac.uk/"
            },
            "resourceAttributes":{
                "required":[],
                "requested":[]
            },
            "description":"",
            "resourceContacts":[
                {
                    "type":"support",
                    "name":"Historical Texts Helpdesk",
                    "email":"mailto:historicaltexts@jisc.ac.uk"
                },
                {
                    "type":"technical",
                    "name":"Jisc Cloud and Connectivity Services",
                    "email":"mailto:servicedesk@jisc.ac.uk"
                }
            ],
            "info":"",
            "privacy":"",
            "entityCategories":[],
            "SirtfiSupport":[]
        }
    ]
}