{
    "generated":"2021-07-20 20:21",
    "en":[
        {
            "catalogID":"846d84831f605962e88ce12122115b5147386865",
            "entityID":"https://proxy.ocre.aai.geant.org/metadata/backend.xml",
            "resourceName":"OCRE SP Proxy",
            "resourceProvider":{
                "name":"GEANT",
                "displayname":"GEANT",
                "url":"https://www.geant.org"
            },
            "resourceAttributes":{
                "required":[
                    "eduPersonUniqueId",
                    "eduPersonTargetedID",
                    "eduPersonPrincipalName",
                    "cn",
                    "displayName",
                    "sn",
                    "givenName",
                    "mail",
                    "eduPersonScopedAffiliation",
                    "schacHomeOrganization"
                ],
                "requested":[
                    "vopersonid",
                    "eduPersonEntitlement"
                ]
            },
            "description":"OCRE Service Provider Proxy",
            "resourceContacts":[
                {
                    "type":"technical",
                    "name":"eduTEAMS Support",
                    "email":"mailto:support+ocre@eduteams.org"
                },
                {
                    "type":"administrative",
                    "name":"eduTEAMS Support",
                    "email":"mailto:support+ocre@eduteams.org"
                },
                {
                    "type":"support",
                    "name":"eduTEAMS Support",
                    "email":"mailto:support+ocre@eduteams.org"
                }
            ],
            "info":"https://wiki.geant.org/display/OSP",
            "privacy":"https://wiki.geant.org/display/OSP/Privacy+Notice",
            "entityCategories":[
                "http://www.geant.net/uri/dataprotection-code-of-conduct/v1"
            ],
            "SirtfiSupport":[]
        }
    ],
    "fr":[
        {
            "catalogID":"846d84831f605962e88ce12122115b5147386865",
            "entityID":"https://proxy.ocre.aai.geant.org/metadata/backend.xml",
            "resourceName":"OCRE SP Proxy",
            "resourceProvider":{
                "name":[],
                "displayname":[],
                "url":"https://www.geant.org"
            },
            "resourceAttributes":{
                "required":[
                    "eduPersonUniqueId",
                    "eduPersonTargetedID",
                    "eduPersonPrincipalName",
                    "cn",
                    "displayName",
                    "sn",
                    "givenName",
                    "mail",
                    "eduPersonScopedAffiliation",
                    "schacHomeOrganization"
                ],
                "requested":[
                    "vopersonid",
                    "eduPersonEntitlement"
                ]
            },
            "description":"",
            "resourceContacts":[
                {
                    "type":"technical",
                    "name":"eduTEAMS Support",
                    "email":"mailto:support+ocre@eduteams.org"
                },
                {
                    "type":"administrative",
                    "name":"eduTEAMS Support",
                    "email":"mailto:support+ocre@eduteams.org"
                },
                {
                    "type":"support",
                    "name":"eduTEAMS Support",
                    "email":"mailto:support+ocre@eduteams.org"
                }
            ],
            "info":"",
            "privacy":"",
            "entityCategories":[
                "http://www.geant.net/uri/dataprotection-code-of-conduct/v1"
            ],
            "SirtfiSupport":[]
        }
    ],
    "it":[
        {
            "catalogID":"846d84831f605962e88ce12122115b5147386865",
            "entityID":"https://proxy.ocre.aai.geant.org/metadata/backend.xml",
            "resourceName":"OCRE SP Proxy",
            "resourceProvider":{
                "name":[],
                "displayname":[],
                "url":"https://www.geant.org"
            },
            "resourceAttributes":{
                "required":[
                    "eduPersonUniqueId",
                    "eduPersonTargetedID",
                    "eduPersonPrincipalName",
                    "cn",
                    "displayName",
                    "sn",
                    "givenName",
                    "mail",
                    "eduPersonScopedAffiliation",
                    "schacHomeOrganization"
                ],
                "requested":[
                    "vopersonid",
                    "eduPersonEntitlement"
                ]
            },
            "description":"",
            "resourceContacts":[
                {
                    "type":"technical",
                    "name":"eduTEAMS Support",
                    "email":"mailto:support+ocre@eduteams.org"
                },
                {
                    "type":"administrative",
                    "name":"eduTEAMS Support",
                    "email":"mailto:support+ocre@eduteams.org"
                },
                {
                    "type":"support",
                    "name":"eduTEAMS Support",
                    "email":"mailto:support+ocre@eduteams.org"
                }
            ],
            "info":"",
            "privacy":"",
            "entityCategories":[
                "http://www.geant.net/uri/dataprotection-code-of-conduct/v1"
            ],
            "SirtfiSupport":[]
        }
    ],
    "de":[
        {
            "catalogID":"846d84831f605962e88ce12122115b5147386865",
            "entityID":"https://proxy.ocre.aai.geant.org/metadata/backend.xml",
            "resourceName":"OCRE SP Proxy",
            "resourceProvider":{
                "name":[],
                "displayname":[],
                "url":"https://www.geant.org"
            },
            "resourceAttributes":{
                "required":[
                    "eduPersonUniqueId",
                    "eduPersonTargetedID",
                    "eduPersonPrincipalName",
                    "cn",
                    "displayName",
                    "sn",
                    "givenName",
                    "mail",
                    "eduPersonScopedAffiliation",
                    "schacHomeOrganization"
                ],
                "requested":[
                    "vopersonid",
                    "eduPersonEntitlement"
                ]
            },
            "description":"",
            "resourceContacts":[
                {
                    "type":"technical",
                    "name":"eduTEAMS Support",
                    "email":"mailto:support+ocre@eduteams.org"
                },
                {
                    "type":"administrative",
                    "name":"eduTEAMS Support",
                    "email":"mailto:support+ocre@eduteams.org"
                },
                {
                    "type":"support",
                    "name":"eduTEAMS Support",
                    "email":"mailto:support+ocre@eduteams.org"
                }
            ],
            "info":"",
            "privacy":"",
            "entityCategories":[
                "http://www.geant.net/uri/dataprotection-code-of-conduct/v1"
            ],
            "SirtfiSupport":[]
        }
    ]
}