{
    "generated":"2021-10-10 18:25",
    "en":[
        {
            "catalogID":"a8c1eb64f8482d3377321dc6611ee0e82ab8c226",
            "entityID":"https://documentos.redclara.net/shibboleth",
            "resourceName":"Document@s - RedCLARA",
            "resourceProvider":{
                "name":"RedCLARA",
                "displayname":"RedCLARA",
                "url":"http://www.redclara.net/"
            },
            "resourceAttributes":{
                "required":[
                    "mail",
                    "surname",
                    "givenName"
                ],
                "requested":[]
            },
            "description":"RedCLARA's Repository of Documents",
            "resourceContacts":[
                {
                    "type":"support",
                    "name":"Authentication Support",
                    "email":"mailto:vsog@redclara.net"
                },
                {
                    "type":"technical",
                    "name":"Technical Support",
                    "email":"mailto:vsog@redclara.net"
                },
                {
                    "type":"administrative",
                    "name":"MarkUrban",
                    "email":"mailto:mark.urban@redclara.net"
                }
            ],
            "info":"http://www.redclara.net/index.php?lang=en",
            "privacy":"",
            "entityCategories":[],
            "SirtfiSupport":[]
        }
    ],
    "fr":[
        {
            "catalogID":"a8c1eb64f8482d3377321dc6611ee0e82ab8c226",
            "entityID":"https://documentos.redclara.net/shibboleth",
            "resourceName":"Document@s",
            "resourceProvider":{
                "name":[],
                "displayname":[],
                "url":"http://www.redclara.net/"
            },
            "resourceAttributes":{
                "required":[
                    "mail",
                    "surname",
                    "givenName"
                ],
                "requested":[]
            },
            "description":"",
            "resourceContacts":[
                {
                    "type":"support",
                    "name":"Authentication Support",
                    "email":"mailto:vsog@redclara.net"
                },
                {
                    "type":"technical",
                    "name":"Technical Support",
                    "email":"mailto:vsog@redclara.net"
                },
                {
                    "type":"administrative",
                    "name":"MarkUrban",
                    "email":"mailto:mark.urban@redclara.net"
                }
            ],
            "info":"",
            "privacy":"",
            "entityCategories":[],
            "SirtfiSupport":[]
        }
    ],
    "it":[
        {
            "catalogID":"a8c1eb64f8482d3377321dc6611ee0e82ab8c226",
            "entityID":"https://documentos.redclara.net/shibboleth",
            "resourceName":"Document@s",
            "resourceProvider":{
                "name":[],
                "displayname":[],
                "url":"http://www.redclara.net/"
            },
            "resourceAttributes":{
                "required":[
                    "mail",
                    "surname",
                    "givenName"
                ],
                "requested":[]
            },
            "description":"",
            "resourceContacts":[
                {
                    "type":"support",
                    "name":"Authentication Support",
                    "email":"mailto:vsog@redclara.net"
                },
                {
                    "type":"technical",
                    "name":"Technical Support",
                    "email":"mailto:vsog@redclara.net"
                },
                {
                    "type":"administrative",
                    "name":"MarkUrban",
                    "email":"mailto:mark.urban@redclara.net"
                }
            ],
            "info":"",
            "privacy":"",
            "entityCategories":[],
            "SirtfiSupport":[]
        }
    ],
    "de":[
        {
            "catalogID":"a8c1eb64f8482d3377321dc6611ee0e82ab8c226",
            "entityID":"https://documentos.redclara.net/shibboleth",
            "resourceName":"Document@s",
            "resourceProvider":{
                "name":[],
                "displayname":[],
                "url":"http://www.redclara.net/"
            },
            "resourceAttributes":{
                "required":[
                    "mail",
                    "surname",
                    "givenName"
                ],
                "requested":[]
            },
            "description":"",
            "resourceContacts":[
                {
                    "type":"support",
                    "name":"Authentication Support",
                    "email":"mailto:vsog@redclara.net"
                },
                {
                    "type":"technical",
                    "name":"Technical Support",
                    "email":"mailto:vsog@redclara.net"
                },
                {
                    "type":"administrative",
                    "name":"MarkUrban",
                    "email":"mailto:mark.urban@redclara.net"
                }
            ],
            "info":"",
            "privacy":"",
            "entityCategories":[],
            "SirtfiSupport":[]
        }
    ]
}