{
    "generated":"2021-07-16 08:27",
    "en":[
        {
            "catalogID":"c01f8f14ed7ed40054d835846cd7fee1698fd98b",
            "entityID":"https://shibboleth2sp.brillonline.nl/shibboleth",
            "resourceName":"https://shibboleth2sp.brillonline.nl/shibboleth",
            "resourceProvider":{
                "name":"Semantico Limited",
                "displayname":"Semantico Limited: Brill Shibboleth 2 SP",
                "url":"http://www.brill.com/"
            },
            "resourceAttributes":{
                "required":[],
                "requested":[]
            },
            "description":"",
            "resourceContacts":[
                {
                    "type":"support",
                    "name":"Helpdesk",
                    "email":"mailto:brill-shibboleth-support@semantico.com"
                },
                {
                    "type":"technical",
                    "name":"Helpdesk",
                    "email":"mailto:brill-shibboleth-support@semantico.com"
                }
            ],
            "info":"",
            "privacy":"",
            "entityCategories":[],
            "SirtfiSupport":[]
        }
    ],
    "fr":[
        {
            "catalogID":"c01f8f14ed7ed40054d835846cd7fee1698fd98b",
            "entityID":"https://shibboleth2sp.brillonline.nl/shibboleth",
            "resourceName":"https://shibboleth2sp.brillonline.nl/shibboleth",
            "resourceProvider":{
                "name":[],
                "displayname":[],
                "url":"http://www.brill.com/"
            },
            "resourceAttributes":{
                "required":[],
                "requested":[]
            },
            "description":"",
            "resourceContacts":[
                {
                    "type":"support",
                    "name":"Helpdesk",
                    "email":"mailto:brill-shibboleth-support@semantico.com"
                },
                {
                    "type":"technical",
                    "name":"Helpdesk",
                    "email":"mailto:brill-shibboleth-support@semantico.com"
                }
            ],
            "info":"",
            "privacy":"",
            "entityCategories":[],
            "SirtfiSupport":[]
        }
    ],
    "it":[
        {
            "catalogID":"c01f8f14ed7ed40054d835846cd7fee1698fd98b",
            "entityID":"https://shibboleth2sp.brillonline.nl/shibboleth",
            "resourceName":"https://shibboleth2sp.brillonline.nl/shibboleth",
            "resourceProvider":{
                "name":[],
                "displayname":[],
                "url":"http://www.brill.com/"
            },
            "resourceAttributes":{
                "required":[],
                "requested":[]
            },
            "description":"",
            "resourceContacts":[
                {
                    "type":"support",
                    "name":"Helpdesk",
                    "email":"mailto:brill-shibboleth-support@semantico.com"
                },
                {
                    "type":"technical",
                    "name":"Helpdesk",
                    "email":"mailto:brill-shibboleth-support@semantico.com"
                }
            ],
            "info":"",
            "privacy":"",
            "entityCategories":[],
            "SirtfiSupport":[]
        }
    ],
    "de":[
        {
            "catalogID":"c01f8f14ed7ed40054d835846cd7fee1698fd98b",
            "entityID":"https://shibboleth2sp.brillonline.nl/shibboleth",
            "resourceName":"https://shibboleth2sp.brillonline.nl/shibboleth",
            "resourceProvider":{
                "name":[],
                "displayname":[],
                "url":"http://www.brill.com/"
            },
            "resourceAttributes":{
                "required":[],
                "requested":[]
            },
            "description":"",
            "resourceContacts":[
                {
                    "type":"support",
                    "name":"Helpdesk",
                    "email":"mailto:brill-shibboleth-support@semantico.com"
                },
                {
                    "type":"technical",
                    "name":"Helpdesk",
                    "email":"mailto:brill-shibboleth-support@semantico.com"
                }
            ],
            "info":"",
            "privacy":"",
            "entityCategories":[],
            "SirtfiSupport":[]
        }
    ]
}